<arqelem>
 <tipo assunto="arqueossitio">
 </tipo>
 <identi>
  Chã do Fojo; Lage Branca
 </identi>
 <descri>
  Necrópole megalítica
 </descri>
 <crono>
  Pré-História Recente
 </crono>
 <lugar>
  Alto de Pebrigue
 </lugar>
 <fregue>
  Gontim
 </fregue>
 <concel>
  Fafe
 </concel>
 <codadm>
  030715
 </codadm>
 <latitu>
  508,7
 </latitu>
 <longit>
  200,5
 </longit>
 <altitu>
  850m
 </altitu>
 <acesso>
  Faz-se pela estrada que sai de Luilhas, em direcção a Vieira do Minho.
 </acesso>
 <quadro>
  Os monumentos localizam-se num planalto que domina Luilhas, próximo do Fojo
de Luilhas.
 </quadro>
 <desarq>
  Duas
  <liga termo="mamoa">
   mamoas
  </liga>
  muito erodidas, já sem esteios, que
deveria pertencer a uma necrópole megalítica que se estendia pelo planalto.
 </desarq>
 <autor>
  Manuela Martins
 </autor>
 <data>
  04-FEV-1998
 </data>
</arqelem>
